{
  "name": "戰慄追求者 ‧ 伊達政宗",
  "attr": "暗",
  "rare": "7",
  "id": "1489",
  "cost": "40",
  "race": "龍類",
  "series": "討伐戰",
  "lvMax": "99",
  "exptype": "10",
  "stats0": "2439,960,39",
  "stats": "2464,966,39",
  "statsMax": "4965,1604,44",
  "exp": "25000+150",
  "sell": "500+100",
  "skill": "龍魂共鳴 ‧ 暗流",
  "lskill": "真龍之源",
  "friend": "0",
  "diamond": "0",
  "newbie": "0",
  "source": "",
  "stage": "[[死亡輾壓]]",
  "story": "瘦削男子靠到石前發出呻吟，他承受痛苦輾轉反側，汗水沾濕滿身，過了好一會，痛楚終於淡去，伊達政宗深呼吸平復氣息。<br>　　『發作間隔縮短了……時間所餘無幾了嗎？』伊達擦拭身體的汗水，三個月前因腹痛難耐便找來醫師診療，結果被診斷出只剩下半年壽命。<br>　　『可恨，我還沒見到更多……』伊達抓緊眼罩，揚起愉悅的笑容。『不過只要在這個島上存活二十八天便得到我想要的。』<br>　　伊達來到這個島後，在某次與狂人戰鬥時遇上壯碩男子武田信玄，兩人合力打倒狂人，武田在之後帶他到據點，並邀伊達加入隊伍裡。本來伊達無意加入，但當見到二刀流劍客宮本武藏後，為了和宮本交手，他改變主意，可惜事如願違，因為那人的存在——<br>　　「伊達，你在哪裡？」健氣女聲呼喊，打斷伊達的沉思，他迎上打扮中性的少女佐佐木小次郎，她是隊伍一員，也是阻礙他和宮本交手的障礙，伊達壓下內心的嫌惡問︰「怎麼了？」「你要和我去打獵。我其實也不想和你一起去，每次和你去不是遇敵襲就是中埋伏，總之就是沒好事。」<br>　　即使佐佐木滿心不悅，但仍和伊達來到林間打獵，很快在岩群間找到野豬。他們躲到石間監視，她舉手示意，兩人從兩方夾擊，順利擒住獵物，他們帶屍體回去據點，途中通往據點的直路被狂人們擋住。<br>　　「我們繞路走吧，他們人多，打起來很有可能會受傷。」佐佐木正想轉頭，伊達卻掠過她，帶著火槍衝到狂人們前掃射，不祥的紫霧自伊達身上冒出，他一臉樂在其中地狂笑起來︰「哈哈哈！來吧來吧，我會把你們統統轟走！」<br>　　狂人們朝伊達蜂擁而上，連帶也發現佐佐木，她被逼拔刀而戰。幾經辛苦，兩人總算打倒所有狂人，但滿身帶傷、灰頭土臉回到據點。<br>　　「這血跡……你們沒事嗎？」二刀流劍客宮本武藏拐著腳迎接，卻被他們的模樣嚇倒，這時佐佐木終於忍不住衝到伊達前，抓住伊達的衣領怒斥︰「你幹嘛衝出去？這很危險，我差點被你累死！」<br>　　「你不覺得很刺激嗎？生命受到威脅的瞬間才能享受到快感，你和宮本對戰不就是為追求這種緊張感嗎？」「你……你這個瘋子！」佐佐木甩開伊達，他嘴角掛著詭異的笑容，眼球轉動，盯住宮本，像蛇盯上獵物一樣。<br>　　「再說比起我，不是有人打著受傷的牌，甚麼也不用做。」「你說甚麼？」佐佐木正要發飆卻被宮本擋住，他直視伊達說︰「很抱歉，我康復後必盡力以作補償。只是，決鬥是為追求真正的武術，並非你所嚮往般。」<br>　　「是嗎？但我覺得你和我是同類人呢。」伊達拋下這句話後便離開，來到河邊清洗火槍。『明明是和我一樣追求著極上的刺激，卻因為那個佐佐木而變成凡人，真沒趣……有沒有方法能令他醒過來呢？』<br>　　「我有辦法可以實現你的願望。」忽然有道聲音自背後響起，伊達連忙蹲下轉身，將火槍瞄上笑臉盈盈的青年服部半藏。<br>　　「是你……有甚麼事？」伊達收起槍但仍沒有放下警戒。<br>　　「你想和宮本比試……不，正確來說，你想感受殺戮、感受潛能被擊發的瞬間。」　　「……你怎麼會知道？你究竟是誰？」<br>　　「這一切不重要，你只要知道我能幫助你實現願望便成。」服部將布袋交給伊達，「將它放進糧食裡，很快就會見到你所想要的。」<br>　　服部說完便離開，留下心生狐疑的伊達，他把袋中物撒到河邊。只見吃到粉末的魚群最後互相殘殺而死，看著舖滿河面的魚屍，伊達忍不住輕笑出聲，他心想︰『這實在太棒了！很快所有人都會變得猙獰、暴戾、嗜血，然後互相撕殺，而我就能在殺戮中得到我想要的快感！』",
  "turn": "0",
  "def": "0"
}