{
  "name": "連肢機偶 · 格蕾琴與海森堡",
  "attr": "水",
  "rare": "6",
  "id": "597",
  "cost": "18",
  "race": "人類",
  "series": "機偶使者",
  "lvMax": "99",
  "exptype": "8",
  "stats0": "1611,698,128",
  "stats": "1620,703,130",
  "statsMax": "2595,1267,342",
  "exp": "900+1000",
  "sell": "1000+100",
  "skill": "攻守自如",
  "lskill": "龍魂輔主1045",
  "refine1": "召喚獸生命力 + 90",
  "refcost1": "50",
  "refine2": "召喚獸進入關卡後技能冷卻回合 - 2",
  "refcost2": "100",
  "refine3": "召喚獸攻擊力 + 120",
  "refcost3": "200",
  "refine4": "移動符石消除角色所在隊伍欄直行的 1 組符石 3 粒或以上，該回合全隊攻擊力提升 10% (不包含掉落符石)",
  "refcost4": "400",
  "refstage": "湛藍機偶的憶念",
  "evofrom": "596",
  "merge": "651",
  "mergeto": "656",
  "mergedesc": "@monster1 和 @monster2 相連時可以合體，同時完全回復生命力",
  "friend": "0",
  "diamond": "0",
  "newbie": "0",
  "source": "",
  "stage": "",
  "story": "「格蕾琴……」海森堡虛弱地喚着女兒。<br/>",
  "turn": "1",
  "def": "10"
}