{
  "name": "賢明魔導 ‧ 主任莫莉",
  "attr": "水",
  "rare": "6",
  "id": "6011",
  "display": "S11",
  "cost": "12",
  "race": "人類",
  "series": "主角",
  "skin": "1",
  "skinfrom": "408",
  "lvMax": "99",
  "exptype": "7",
  "stats0": "1186,640,158",
  "stats": "1196,645,160",
  "statsMax": "2260,1231,384",
  "exp": "10000+900",
  "sell": "800+100",
  "skill": "界限突破 ‧ 水",
  "lskill": "海之怒",
  "refine1": "召喚獸回復力 + 20",
  "refcost1": "50",
  "refine2": "召喚獸進入關卡後技能冷卻回合 - 2",
  "refcost2": "150",
  "refine3": "召喚獸攻擊力 + 120",
  "refcost3": "300",
  "refine4": "移動符石消除角色所在隊伍欄直行的 1 組符石 4 粒或以上，該回合全隊攻擊力提升 10% (不包含掉落符石)",
  "refcost4": "500",
  "refstage": "涓流的追憶",
  "friend": "0",
  "diamond": "0",
  "newbie": "0",
  "source": "[[召喚師聯賽]] 第八季兌換獎賞",
  "stage": "",
  "story": "賢者莫莉和她的同伴被譽為人類的英雄。他們阻止魔族佔領以諾塔，更攀登上塔的斷層。莫莉與同伴都為對抗混亂而犧牲，為人們帶來稍息的和<br/>",
  "notes": "當隊長為{{479|30}}時，觸發[[隊伍技能]]「聖靈傳承」，主動技能改為「額外增加 3 行符石，移動符石時間延長至 15 秒，可於時間內任意移動符石而不會發動消除，並提升水屬性的攻擊力」",
  "turn": "2",
  "def": "20"
}