{
  "name": "無限決意 ‧ 妮亞",
  "attr": "光",
  "rare": "6",
  "id": "6372",
  "display": "S372",
  "cost": "16",
  "race": "人類",
  "series": "天元突破、大紅蓮團",
  "lvMax": "99",
  "exptype": "10",
  "stats0": "1403,709,236",
  "stats": "1417,716,239",
  "statsMax": "2821,1425,546",
  "exp": "1200+1000",
  "sell": "6000+100",
  "skill": "希望之光",
  "lskill": "天元突破之勢",
  "refine1": "召喚獸生命力 + 120",
  "refcost1": "50",
  "refine2": "移動符石消除角色所在隊伍欄直行的 1 組符石 3 粒或以上，該回合全隊回復力提升 10% (不包含掉落符石)",
  "refcost2": "150",
  "refine3": "召喚獸攻擊力 + 90",
  "refcost3": "300",
  "refine4": "移動符石消除角色所在隊伍欄直行的 1 組符石 4 粒或以上，該回合全隊攻擊力提升 10% (不包含掉落符石)",
  "refcost4": "500",
  "refstage": "妮亞的昇華",
  "skinfrom": "2410",
  "friend": "0",
  "diamond": "0",
  "source": "",
  "stage": "",
  "story": "<poem>西蒙在谷底被遺棄的箱子中找到的少女。為螺旋王羅傑儂的第一王女。",
  "turn": "0",
  "def": "0"
}