{
  "name": "窳敗之瞳 ‧ 美杜莎",
  "attr": "木",
  "rare": "6",
  "id": "853",
  "cost": "12",
  "race": "獸類",
  "series": "西方魔獸",
  "lvMax": "99",
  "exptype": "8",
  "stats0": "1614,554,57",
  "stats": "1706,586,61",
  "statsMax": "3601,1249,152",
  "exp": "2400+3700",
  "sell": "700+100",
  "skill": "石化之力",
  "lskill": "木之怒嘯 ‧ 獸",
  "refine1": "召喚獸生命力 + 180",
  "refcost1": "50",
  "refine2": "召喚獸進入關卡後技能冷卻回合 - 3",
  "refcost2": "100",
  "refine3": "召喚獸攻擊力 + 140",
  "refcost3": "200",
  "refine4": "召喚獸進入關卡後技能冷卻回合 - 4",
  "refcost4": "400",
  "refstage": "諸神的寵獸 ‧ 木",
  "relfrom": "184",
  "friend": "0",
  "diamond": "0",
  "newbie": "0",
  "source": "",
  "stage": "",
  "story": "美杜莎總是用眼睛說話，她的頭顱沉默地置在雅典娜的殿中，以幽怨的神情誘人凝望。<br/>",
  "turn": "0",
  "def": "0"
}