{
  "name": "御靈聖女 ‧ 李憶如",
  "attr": "火",
  "rare": "6",
  "id": "904",
  "cost": "14",
  "race": "人類",
  "series": "仙劍靈傑",
  "lvMax": "99",
  "exptype": "10",
  "stats0": "1135,763,182",
  "stats": "1147,770,184",
  "statsMax": "2367,1483,408",
  "exp": "1800+800",
  "sell": "5000+200",
  "skill": "蓄能轉換 ‧ 火",
  "lskill": "火燄舞影",
  "refine1": "召喚獸生命力 + 100",
  "refcost1": "50",
  "refine2": "移動符石消除角色所在隊伍欄直行的 1 組符石 4 粒或以上，該回合全隊攻擊力提升 10% (不包含掉落符石)",
  "refcost2": "150",
  "refine3": "召喚獸攻擊力 + 130",
  "refcost3": "300",
  "refine4": "召喚獸主動技變為 蓄能轉換 ‧ 煉火",
  "refcost4": "500",
  "refstage": "芙蓉紅顏逍遙女",
  "evofrom": "903",
  "friend": "0",
  "diamond": "0",
  "newbie": "0",
  "source": "",
  "stage": "",
  "story": "「人的命、妖的命，到底哪一個比較重要？如果殺害妖怪來救治人命是對的事情，妖怪吃人為生又為何是錯？大家的目的，都只是要活下去而已，不是嗎？我雖然是人，但也擁有不屬於人的部分……」<br/>",
  "turn": "0",
  "def": "0",
  "teamskill2": ""
}