{
  "openhis": [
    {
      "start": "2020/11/20 22:00",
      "end": "2020/11/23 23:59",
      "note": "",
      "cj": [
        {
          "star": "3",
          "id": "C292",
          "soul": "",
          "m": "",
          "num": "1"
        }
      ],
      "cishujl": [
        {
          "cs_jltj": "成功通过 [U]() 3 次",
          "cs_jl": "![2510](zhs/2510i.png) * 1(技能等级 7) "
        }
      ]
    }
  ],
  "cjtimes": 1,
  "stages": [
    {
      "id": "2510",
      "title": "要團員進步之路 地獄級",
      "cj": [
        "隊伍中只有光屬性的成員  (不包括隊伍技能)",
        "隊伍中只有魔族成員",
        "隊伍中有 5 種屬性的成員  (不包括隊伍技能)"
      ],
      "data": [
        {
          "card": "387",
          "stage": "1{{掉落*白金}}",
          "damage": "6666",
          "turn": "6{{初始CD*6}}",
          "hp": "666000000",
          "def": "666000",
          "coin": "",
          "lv": "1",
          "es": "365",
          "note": "",
          "esjson": {
            "img": "es/SI132.png",
            "title": "扣血100%"
          },
          "jd": ""
        },
        {
          "card": "387",
          "stage": "",
          "damage": "6666",
          "turn": "6{{初始CD*6}}",
          "hp": "666000000",
          "def": "666000",
          "coin": "",
          "lv": "1",
          "es": "365",
          "note": "",
          "esjson": {
            "img": "es/SI132.png",
            "title": "扣血100%"
          },
          "jd": ""
        },
        {
          "card": "2322",
          "stage": "2",
          "damage": "20361",
          "turn": "1{{初始CD*1}}",
          "hp": "189605420",
          "def": "1380000",
          "coin": "",
          "es": "2322",
          "note": "",
          "esjson": {
            "img": "es/SI122.png|es/SI157.png|es/SI048.png",
            "title": "獵魔外-禁錮-無視減傷 ‧ 剋屬盾-棄攻轉屬"
          },
          "jd": ""
        },
        {
          "card": "2325",
          "stage": "3{{雙血}}",
          "damage": "18733",
          "turn": "1{{初始CD*1}}",
          "hp": "276028720",
          "def": "1180000",
          "coin": "",
          "es": "3842",
          "note": "",
          "esjson": {
            "img": "es/SI160.png|es/SI265.png|es/SI107.png|es/SI124.png",
            "title": "突擊10% ‧ 八重碎裂 ‧ 9+Combo追擊盾 ‧ 無法控制"
          },
          "jd": ""
        },
        {
          "card": "2325",
          "stage": "",
          "damage": "100",
          "turn": "3",
          "hp": "590517830",
          "def": "1180000",
          "coin": "",
          "es": "3565",
          "note": "",
          "esjson": {
            "img": "es/SI159.png|es/SI315.png|es/SI132.png|es/SI250.png",
            "title": "CD3 ‧ 首回光引爆射擊 ‧ 同歸於盡 ‧ 首消23顆符石盾"
          },
          "jd": ""
        },
        {
          "card": "2326",
          "stage": "4",
          "damage": "24909",
          "turn": "1{{初始CD*1}}",
          "hp": "403567450",
          "def": "1860000",
          "coin": "",
          "es": "1743",
          "note": "",
          "esjson": {
            "img": "es/SI233.png|es/SI161.png|es/SI215.png|es/SI183.png",
            "title": "(5回回復力減弱90%) ‧ 命懸一線 ‧ 黑白符石 ‧ 始終盾"
          },
          "jd": ""
        },
        {
          "card": "2323",
          "stage": "5{{雙血}}",
          "damage": "20456",
          "turn": "1{{初始CD*1}}",
          "hp": "262587820",
          "def": "1490000",
          "coin": "",
          "es": "3576",
          "note": "",
          "esjson": {
            "img": "es/SI002.png|es/SI229.png|es/SI047.png|es/SI302.png|es/SI114.png",
            "title": "火屬防禦盾 ‧ 四重燃燒50%-符石轉火 ‧ 首消火追擊零化"
          },
          "jd": ""
        },
        {
          "card": "2323",
          "stage": "",
          "damage": "31520",
          "turn": "1",
          "hp": "510876590",
          "def": "1490000",
          "coin": "",
          "es": "4230",
          "note": "",
          "esjson": {
            "img": "es/SI159.png|es/SI017.png|es/SI047.png|es/SI229.png|es/SI144.png|es/SI292.png",
            "title": "CD1 ‧ 敵轉火 ‧ 首回二四橫行轉火燃燒20% ‧ 燃燒轉火 ‧ 首消火傷害零化-反擊200% ‧ 凍結盾90% ‧ 凍敵滅火"
          },
          "jd": ""
        },
        {
          "card": "2324",
          "stage": "6",
          "damage": "74295",
          "turn": "2{{初始CD*2}}",
          "hp": "850000000",
          "def": "2300000",
          "coin": "",
          "es": "2865",
          "note": "",
          "esjson": {
            "img": "es/SI250.png|es/SI337.png|es/SI212.png",
            "title": "循環累積15+同屬符石盾 ‧ 火弱化鎖定20% ‧ 無限回復"
          },
          "jd": ""
        },
        {
          "card": "2510",
          "stage": "7{{雙血}}{{掉落*白金}}",
          "damage": "23174",
          "turn": "1{{初始CD*1}}",
          "hp": "342082560",
          "def": "5750000",
          "coin": "",
          "es": "3507",
          "note": "",
          "esjson": {
            "img": "es/SI224.png|es/SI108.png",
            "title": "軌跡隱藏 ‧ 10+Combo追擊盾"
          },
          "jd": ""
        },
        {
          "card": "2510",
          "stage": "",
          "damage": "100",
          "turn": "1",
          "hp": "758718250",
          "def": "5750000",
          "coin": "",
          "lv": "1",
          "es": "3442",
          "note": "",
          "esjson": {
            "img": "es/SI159.png|es/SI248.png|es/SI132.png|es/SI124.png",
            "title": "首攻CD2 ‧ 強化五屬盾 ‧ 扣血100% ‧ 無法控制"
          },
          "jd": ""
        }
      ]
    }
  ]
}