{
  "openhis": [],
  "cj": [],
  "stages": [
    {
      "id": "387",
      "title": "魔族的詛咒",
      "note": "",
      "story": "{{故事|{{StoryDialog}}\n{{召喚師|50}}'''{{召喚師名稱}}：'''「洛基！你們現在是要去費雷……華納族那裡吧？我也要一起去！」<br/>\n{{1563|50}}'''凱拉：'''「好啊！{{召喚師名稱}}也一起去，凱拉與芬爾厄才沒那麼悶呢！」<br/>\n{{510|50}}'''洛基：'''「不，你不可以一起去，你的一切都太可疑了。」<br/>\n{{召喚師|50}}'''{{召喚師名稱}}：'''「可、可是……」<br/>\n{{510|50}}'''洛基：'''「不要逼我把同樣的話說兩遍。你喜歡去哪都好，就是不要跟著我們。」<br/>\n{{召喚師|50}}'''{{召喚師名稱}}：'''「我知道怎樣才能舒緩凱拉身上被魔族所下的詛咒，那個由你妻子轉移到她身上的詛咒。」<br/>\n　　語音未落，洛基憤怒地衝向召喚師，一手握住召喚師的頸項，將召喚師整個人提至半空。此時，洛基留意到召喚師變得透明的四肢。神情不禁錯愕。他緩緩把召喚師放下，別過臉去。<br/>\n{{510|50}}'''洛基：'''『看來那傢伙也中了魔族的詛咒…… 難怪會知道安爾伯達的事。』<br/>\n{{510|50}}'''洛基：'''「你要跟來便跟來吧！只是，別忘記你說過你有方法能幫助凱拉。」<br/>\n\n{{StoryDialog|B}}\n　　在洛基的帶領下，召喚師、凱拉、芬爾厄與眾士兵便按著地圖前進。他們在極冰之地前進著，以夜空上的星星作指標。<br/>\n　　為了趕上戰線，洛基等人不分晝夜前進，每天只休息一小會，終來到華納族的領域，卻遲遲去不到戰場。召喚師覺得他們總是在同一個地方轉圈，像中了陷阱……<br/>\n{{387|50}}'''：'''「嘻嘻，你們已中了我的陷阱！束手無策對吧？」<br/>\n\n{{StoryDialog|C}}\n{{召喚師|50}}'''{{召喚師名稱}}：'''「那作為指標的北極星好像有哪裡古怪的……」<br/>\n{{510|50}}'''洛基：'''「哼，是哪裡古怪了？北極星一直都是在……」<br/>\n　　聽了召喚師的說話，洛基看向北極星並以手比劃著方向與坐標，赫然發現這並非北極星，而是一個以元素之力而成的光球！<br/>",
      "cj": [],
      "info": {
        "sta": "15",
        "battle": "4",
        "exp": "1125"
      },
      "data": [
        {
          "card": "510",
          "stage": "1",
          "turn": "1(1)",
          "hp": "100",
          "def": "10",
          "coin": "6383",
          "es": "87",
          "note": "",
          "esjson": {
            "img": "es/SI125.png",
            "title": "技能回復"
          },
          "jd": ""
        },
        {
          "card": "067",
          "stage": "2~3{{隨機*2~3}}",
          "turn": "1",
          "hp": "953590",
          "def": "1730",
          "lv": "15",
          "coin": "291",
          "note": "",
          "esjson": null,
          "jd": ""
        },
        {
          "card": "329",
          "stage": "",
          "turn": "3",
          "hp": "836438",
          "def": "1620",
          "lv": "15",
          "drop": "097",
          "coin": "277",
          "note": "",
          "esjson": null,
          "jd": ""
        },
        {
          "card": "1526",
          "stage": "",
          "turn": "2",
          "hp": "562974",
          "def": "2630",
          "lv": "15",
          "coin": "566",
          "note": "",
          "esjson": null,
          "jd": ""
        },
        {
          "card": "387",
          "stage": "4",
          "turn": "1(1)",
          "hp": "8297380",
          "def": "4920",
          "coin": "600",
          "chest": "4000",
          "es": "1462",
          "note": "",
          "esjson": {
            "img": "es/SI121.png|es/SI123.png|es/SI228.png|es/SI131.png",
            "title": "附加消除重置 ‧ 四角黏附 ‧ 扣血90%"
          },
          "jd": ""
        }
      ]
    },
    {
      "id": "339",
      "title": "虛假的指標",
      "note": "",
      "story": "{{故事|{{StoryDialog}}\n　　召喚師與洛基等人，一直都以北極星作為指標，朝著華納族的所在地前進，卻沒想到原來已中了魔族的陷阱——他們一直作為指標的北極星，原來是魔族用強大的光元素之力造出來，藉以欺騙他們。<br/>\n{{召喚師|50}}'''{{召喚師名稱}}：'''「這種兒戲的偽裝就由我來打破吧！」<br/>\n　　召喚師喚出英靈，英靈將箭瞄準光球，木元素之力聚於箭頭…… 手一放，帶著木元素的箭便閃著綠光地射向光球！光球迸裂出強光後，慢慢淡去並消失於夜空中，而真正的北極星在光球被摧毀後再度出現，洛基等人終可繼續朝戰場前進。<br/>\n{{510|50}}'''洛基：'''「很不錯，能發現那是顆假的北極星，並將它摧毀，不然我們此刻仍被魔族耍得團團轉。」<br/>\n{{召喚師|50}}'''{{召喚師名稱}}：'''「你是想跟我道謝吧？」<br/>\n{{510|50}}'''洛基：'''「……你喜歡怎樣想就怎樣想吧。」<br/>\n\n{{StoryDialog|W|W1=三}}\n{{066|50}}'''：'''「請、請你們救救我…… 魔族在追殺我……」<br/>\n\n{{StoryDialog|WC|W1=三|WC1=放生{{066|_name}}}}\n{{066|50}}'''：'''「全賴有你們，我才得以沒事，謝謝你們！」<br/>\n\n{{StoryDialog|B}}\n　　他們按著地圖前進，終來到了華納族領域。然迎面而來的，卻是戰爭的峰煙，還有遍地的屍骸……<br/>\n{{召喚師|50}}'''{{召喚師名稱}}：'''「難、難道我們始終是來遲了一步？」<br/>\n{{510|50}}'''洛基：'''「別想些有的沒的，趕快繼續前進吧。」<br/>\n\n{{StoryDialog|C}}\n　　正當他們朝華納族的部落繼續前進時，不遠處忽然傳來陣陣巨響！洛基與召喚師等人朝巨響的方向看去，便見華納族正與魔族激烈地戰鬥著，而帶領著華納族的，正是華納族的首領費雷。<br/>",
      "cj": [
        "虛影世界讓 ![066](zhs/066i.png) 離開 1 次 —— 獲得龍刻獎賞 ![C170漩之獸暴龍紋](lk/C170.png)[C170漩之獸暴龍紋](/pages/index/lk/lk?id=C170) "
      ],
      "info": {
        "sta": "15",
        "battle": "5",
        "exp": "1125"
      },
      "data": [
        {
          "card": "077",
          "stage": "",
          "turn": "4",
          "hp": "980982",
          "def": "2140",
          "lv": "15",
          "coin": "283",
          "note": "",
          "esjson": null,
          "jd": ""
        },
        {
          "card": "1526",
          "stage": "",
          "turn": "3",
          "hp": "562974",
          "def": "2630",
          "lv": "15",
          "coin": "566",
          "note": "",
          "esjson": null,
          "jd": ""
        },
        {
          "card": "1531",
          "stage": "",
          "turn": "1",
          "hp": "472363",
          "def": "3180",
          "lv": "15",
          "coin": "474",
          "note": "",
          "esjson": null,
          "jd": ""
        },
        {
          "card": "1526",
          "stage": "3",
          "turn": "2(2)",
          "hp": "562974",
          "def": "2630",
          "coin": "566",
          "es": "35",
          "note": "",
          "esjson": {
            "img": "es/SI129.png",
            "title": "扣血70%"
          },
          "jd": ""
        },
        {
          "card": "066",
          "stage": "",
          "turn": "9(9)",
          "hp": "98651",
          "def": "10",
          "coin": "280",
          "note": "{{特性*離開*9}}",
          "esjson": null,
          "jd": ""
        },
        {
          "card": "1526",
          "stage": "",
          "turn": "2(1)",
          "hp": "562974",
          "def": "2630",
          "coin": "566",
          "es": "35",
          "note": "",
          "esjson": {
            "img": "es/SI129.png",
            "title": "扣血70%"
          },
          "jd": ""
        },
        {
          "card": "339",
          "stage": "5",
          "turn": "1(1)",
          "hp": "3429350",
          "def": "7180",
          "coin": "493",
          "chest": "4000",
          "es": "494",
          "note": "",
          "esjson": {
            "img": "es/SI219.png",
            "title": "四重凍結"
          },
          "jd": ""
        }
      ]
    },
    {
      "id": "1110",
      "title": "兩軍相會",
      "note": "※ 首次通關 可獲得1粒 ![魔法石](toswikiapic/Gift-魔法石.png) ※",
      "story": "{{故事|{{StoryDialog}}\n　　召喚師與洛基等人來到華納族的領域，便見費雷正帶領著華納族一眾與魔族激戰著。此時，費雷高舉勝利之劍，水元素便開始於上空聚集，一道水龍捲慢慢形成，將眾多的魔兵捲進水龍捲中！一時將場上的魔族士兵盡數擊飛。<br/>\n　　然而，那被捲上水龍捲的魔族士兵，只屬於來襲華納族的魔族大軍的一小部分，真正的大軍這才慢慢出現……<br/>\n\n{{StoryDialog|W|W1=二}}\n{{召喚師|50}}'''{{召喚師名稱}}：'''「別呆住了！我們不是來救援的嗎？洛基！」<br/>\n{{510|50}}'''洛基：'''「我做事不需你來命令！全軍出擊！」<br/>\n\n{{StoryDialog|B}}\n　　在洛基的帶領下，眾士兵從小山衝向魔族大軍，與費雷的華納族軍隊從前方與側邊夾擊魔族大軍！洛基他們的突襲，殺魔族大軍一個措手不及，使魔族大軍不得不分散成數個小隊，只是魔族大軍的數量仍然很多，突擊就是再有效，都無助改變現時的戰局。<br/>\n{{1110|50}}'''：'''「將他們包圍！廢物一般的人類，不用怕他們！」<br/>\n\n{{StoryDialog|C}}\n{{510|50}}'''洛基：'''「看來在苦戰呢，費雷。」<br/>\n{{1022|50}}'''費雷：'''「哼！你的出現打亂了我的節奏！」<br/>\n　　在洛基召喚師與等人奮戰下，終成功殺出一條血路，來到與費雷的軍隊匯合。洛基與費雷背靠背來戰鬥，華納族的士兵見到洛基等來支援，頓時士氣大升。<br/>",
      "cj": [
        "虛影世界完成關卡[兩軍相會]()——開放關卡[華納族戰役](/pages/index/detail/detail?name2=%E8%8F%AF%E7%B4%8D%E6%97%8F%E6%88%B0%E5%BD%B9)"
      ],
      "info": {
        "sta": "25",
        "battle": "5",
        "exp": "2500"
      },
      "data": [
        {
          "card": "085",
          "stage": "",
          "turn": "4",
          "hp": "962315",
          "def": "2090",
          "coin": "283",
          "lv": "15",
          "note": "",
          "esjson": null,
          "jd": ""
        },
        {
          "card": "1530",
          "stage": "",
          "turn": "3",
          "hp": "552432",
          "def": "2620",
          "coin": "566",
          "lv": "15",
          "note": "",
          "esjson": null,
          "jd": ""
        },
        {
          "card": "490",
          "stage": "3",
          "turn": "2(2)",
          "hp": "1524690",
          "def": "1520",
          "coin": "209",
          "note": "",
          "esjson": null,
          "jd": ""
        },
        {
          "card": "490",
          "stage": "",
          "turn": "2(1)",
          "hp": "1524690",
          "def": "1520",
          "coin": "209",
          "es": "39",
          "note": "",
          "esjson": {
            "img": "es/SI164.png|es/SI165.png",
            "title": "召喚小怪 ‧ 2秒轉珠"
          },
          "jd": ""
        },
        {
          "card": "490",
          "stage": "",
          "turn": "2(2)",
          "hp": "1524690",
          "def": "1520",
          "coin": "209",
          "note": "",
          "esjson": null,
          "jd": ""
        },
        {
          "card": "585",
          "stage": "4",
          "turn": "1(1)",
          "hp": "4597160",
          "def": "3840",
          "coin": "249",
          "es": "876",
          "note": "",
          "esjson": {
            "img": "es/SI188.png|es/SI254.png",
            "title": "越攻越強 ‧ 強化盾-非強化傷害吸收"
          },
          "jd": ""
        },
        {
          "card": "1110",
          "stage": "5",
          "turn": "1(1)",
          "hp": "8935240",
          "def": "19240",
          "coin": "6383",
          "chest": "8000",
          "es": "860",
          "note": "",
          "esjson": {
            "img": "es/SI345.png|es/SI122.png",
            "title": "剋獸-防禦80%-獸側技能封鎖"
          },
          "jd": "R5特性场景特性：10098"
        }
      ]
    }
  ]
}